Workbook
Name listaCategorias: Categorias!$G$2:$G$20
Name listaContas: Categorias!$K$2:$K$7
Name listaFormas: Categorias!$I$2:$I$9
Name listaStatus: Categorias!$M$2:$M$4
Name listaTipos: Categorias!$A$2:$A$3

Sheet Lancamentos
A1: Data | B1: Tipo | C1: Categoria | D1: Subcategoria | E1: Descricao | F1: Forma | G1: Conta | H1: Valor | I1: Mes | J1: Status | K1: Observacoes
A2: 46181 | B2: Receita | C2: Salario | E2: Salario mensal | F2: Transferencia | G2: Conta Corrente | H2: 4500 | I2: =IF(A2="","",TEXT(A2,"yyyy-mm")) -> yyyy-06 | J2: Pago | K2: Exemplo: apague ou substitua
A3: 46183 | B3: Despesa | C3: Moradia | D3: Aluguel | E3: Aluguel | F3: Pix | G3: Conta Corrente | H3: 1200 | I3: =IF(A3="","",TEXT(A3,"yyyy-mm")) -> yyyy-06 | J3: Pago | K3: Exemplo
A4: 46185 | B4: Despesa | C4: Alimentacao | D4: Mercado | E4: Compra do mes | F4: Cartao Debito | G4: Conta Corrente | H4: 650 | I4: =IF(A4="","",TEXT(A4,"yyyy-mm")) -> yyyy-06 | J4: Pago | K4: Exemplo
A5: 46188 | B5: Despesa | C5: Transporte | D5: Combustivel | E5: Abastecimento | F5: Cartao Credito | G5: Cartao 1 | H5: 220 | I5: =IF(A5="","",TEXT(A5,"yyyy-mm")) -> yyyy-06 | J5: Pendente | K5: Exemplo
I6: =IF(A6="","",TEXT(A6,"yyyy-mm"))
I7: =IF(A7="","",TEXT(A7,"yyyy-mm"))
I8: =IF(A8="","",TEXT(A8,"yyyy-mm"))
I9: =IF(A9="","",TEXT(A9,"yyyy-mm"))
I10: =IF(A10="","",TEXT(A10,"yyyy-mm"))
I11: =IF(A11="","",TEXT(A11,"yyyy-mm"))
I12: =IF(A12="","",TEXT(A12,"yyyy-mm"))
I13: =IF(A13="","",TEXT(A13,"yyyy-mm"))
I14: =IF(A14="","",TEXT(A14,"yyyy-mm"))
I15: =IF(A15="","",TEXT(A15,"yyyy-mm"))
I16: =IF(A16="","",TEXT(A16,"yyyy-mm"))
I17: =IF(A17="","",TEXT(A17,"yyyy-mm"))
... I501: =IF(A501="","",TEXT(A501,"yyyy-mm"))

Sheet Categorias
A1: Tipos | C1: Categorias de Despesa | E1: Categorias de Receita | G1: Todas as Categorias | I1: Formas | K1: Contas | M1: Status
A2: Receita | C2: Moradia | E2: Salario | G2: Salario | I2: Pix | K2: Conta Corrente | M2: Pago
A3: Despesa | C3: Alimentacao | E3: Freelance | G3: Freelance | I3: Cartao Debito | K3: Carteira | M3: Pendente
C4: Transporte | E4: Investimentos | G4: Investimentos | I4: Cartao Credito | K4: Poupanca | M4: Previsto
C5: Saude | E5: Reembolsos | G5: Reembolsos | I5: Dinheiro | K5: Cartao 1
C6: Educacao | E6: Vendas | G6: Vendas | I6: Boleto | K6: Cartao 2
C7: Lazer | E7: Presente | G7: Presente | I7: Transferencia | K7: Investimentos
C8: Assinaturas | E8: Outros | G8: Outros | I8: Debito Automatico
C9: Compras | G9: Moradia | I9: Outro
C10: Impostos | G10: Alimentacao
C11: Dividas | G11: Transporte
C12: Pets | G12: Saude
C13: Familia | G13: Educacao
C14: Outros | G14: Lazer
G15: Assinaturas
G16: Compras
G17: Impostos
G18: Dividas
G19: Pets
G20: Familia

Sheet Resumo Mensal
A1: Mes | B1: Receitas | C1: Despesas | D1: Saldo | E1: Taxa de Poupanca | G1: Categoria Despesa | H1: Total | I1: Participacao
A2: 2026-01 | B2: =SUMIFS(Lancamentos!$H:$H,Lancamentos!$B:$B,"Receita",Lancamentos!$I:$I,A2) -> 0 | C2: =SUMIFS(Lancamentos!$H:$H,Lancamentos!$B:$B,"Despesa",Lancamentos!$I:$I,A2) -> 0 | D2: =B2-C2 -> 0 | E2: =IF(B2=0,0,D2/B2) -> 0 | G2: Moradia | H2: =SUMIFS(Lancamentos!$H:$H,Lancamentos!$B:$B,"Despesa",Lancamentos!$C:$C,G2) -> 1200 | I2: =IF(SUM(H2:H14)=0,0,H2/SUM(H2:H14)) -> 0.57971014
A3: 2026-02 | B3: =SUMIFS(Lancamentos!$H:$H,Lancamentos!$B:$B,"Receita",Lancamentos!$I:$I,A3) -> 0 | C3: =SUMIFS(Lancamentos!$H:$H,Lancamentos!$B:$B,"Despesa",Lancamentos!$I:$I,A3) -> 0 | D3: =B3-C3 -> 0 | E3: =IF(B3=0,0,D3/B3) -> 0 | G3: Alimentacao | H3: =SUMIFS(Lancamentos!$H:$H,Lancamentos!$B:$B,"Despesa",Lancamentos!$C:$C,G3) -> 650 | I3: =IF(SUM(H2:H14)=0,0,H3/SUM(H2:H14)) -> 0.31400966
A4: 2026-03 | B4: =SUMIFS(Lancamentos!$H:$H,Lancamentos!$B:$B,"Receita",Lancamentos!$I:$I,A4) -> 0 | C4: =SUMIFS(Lancamentos!$H:$H,Lancamentos!$B:$B,"Despesa",Lancamentos!$I:$I,A4) -> 0 | D4: =B4-C4 -> 0 | E4: =IF(B4=0,0,D4/B4) -> 0 | G4: Transporte | H4: =SUMIFS(Lancamentos!$H:$H,Lancamentos!$B:$B,"Despesa",Lancamentos!$C:$C,G4) -> 220 | I4: =IF(SUM(H2:H14)=0,0,H4/SUM(H2:H14)) -> 0.10628019
A5: 2026-04 | B5: =SUMIFS(Lancamentos!$H:$H,Lancamentos!$B:$B,"Receita",Lancamentos!$I:$I,A5) -> 0 | C5: =SUMIFS(Lancamentos!$H:$H,Lancamentos!$B:$B,"Despesa",Lancamentos!$I:$I,A5) -> 0 | D5: =B5-C5 -> 0 | E5: =IF(B5=0,0,D5/B5) -> 0 | G5: Saude | H5: =SUMIFS(Lancamentos!$H:$H,Lancamentos!$B:$B,"Despesa",Lancamentos!$C:$C,G5) -> 0 | I5: =IF(SUM(H2:H14)=0,0,H5/SUM(H2:H14)) -> 0
A6: 2026-05 | B6: =SUMIFS(Lancamentos!$H:$H,Lancamentos!$B:$B,"Receita",Lancamentos!$I:$I,A6) -> 0 | C6: =SUMIFS(Lancamentos!$H:$H,Lancamentos!$B:$B,"Despesa",Lancamentos!$I:$I,A6) -> 0 | D6: =B6-C6 -> 0 | E6: =IF(B6=0,0,D6/B6) -> 0 | G6: Educacao | H6: =SUMIFS(Lancamentos!$H:$H,Lancamentos!$B:$B,"Despesa",Lancamentos!$C:$C,G6) -> 0 | I6: =IF(SUM(H2:H14)=0,0,H6/SUM(H2:H14)) -> 0
A7: 2026-06 | B7: =SUMIFS(Lancamentos!$H:$H,Lancamentos!$B:$B,"Receita",Lancamentos!$I:$I,A7) -> 0 | C7: =SUMIFS(Lancamentos!$H:$H,Lancamentos!$B:$B,"Despesa",Lancamentos!$I:$I,A7) -> 0 | D7: =B7-C7 -> 0 | E7: =IF(B7=0,0,D7/B7) -> 0 | G7: Lazer | H7: =SUMIFS(Lancamentos!$H:$H,Lancamentos!$B:$B,"Despesa",Lancamentos!$C:$C,G7) -> 0 | I7: =IF(SUM(H2:H14)=0,0,H7/SUM(H2:H14)) -> 0
A8: 2026-07 | B8: =SUMIFS(Lancamentos!$H:$H,Lancamentos!$B:$B,"Receita",Lancamentos!$I:$I,A8) -> 0 | C8: =SUMIFS(Lancamentos!$H:$H,Lancamentos!$B:$B,"Despesa",Lancamentos!$I:$I,A8) -> 0 | D8: =B8-C8 -> 0 | E8: =IF(B8=0,0,D8/B8) -> 0 | G8: Assinaturas | H8: =SUMIFS(Lancamentos!$H:$H,Lancamentos!$B:$B,"Despesa",Lancamentos!$C:$C,G8) -> 0 | I8: =IF(SUM(H2:H14)=0,0,H8/SUM(H2:H14)) -> 0
A9: 2026-08 | B9: =SUMIFS(Lancamentos!$H:$H,Lancamentos!$B:$B,"Receita",Lancamentos!$I:$I,A9) -> 0 | C9: =SUMIFS(Lancamentos!$H:$H,Lancamentos!$B:$B,"Despesa",Lancamentos!$I:$I,A9) -> 0 | D9: =B9-C9 -> 0 | E9: =IF(B9=0,0,D9/B9) -> 0 | G9: Compras | H9: =SUMIFS(Lancamentos!$H:$H,Lancamentos!$B:$B,"Despesa",Lancamentos!$C:$C,G9) -> 0 | I9: =IF(SUM(H2:H14)=0,0,H9/SUM(H2:H14)) -> 0
A10: 2026-09 | B10: =SUMIFS(Lancamentos!$H:$H,Lancamentos!$B:$B,"Receita",Lancamentos!$I:$I,A10) -> 0 | C10: =SUMIFS(Lancamentos!$H:$H,Lancamentos!$B:$B,"Despesa",Lancamentos!$I:$I,A10) -> 0 | D10: =B10-C10 -> 0 | E10: =IF(B10=0,0,D10/B10) -> 0 | G10: Impostos | H10: =SUMIFS(Lancamentos!$H:$H,Lancamentos!$B:$B,"Despesa",Lancamentos!$C:$C,G10) -> 0 | I10: =IF(SUM(H2:H14)=0,0,H10/SUM(H2:H14)) -> 0
A11: 2026-10 | B11: =SUMIFS(Lancamentos!$H:$H,Lancamentos!$B:$B,"Receita",Lancamentos!$I:$I,A11) -> 0 | C11: =SUMIFS(Lancamentos!$H:$H,Lancamentos!$B:$B,"Despesa",Lancamentos!$I:$I,A11) -> 0 | D11: =B11-C11 -> 0 | E11: =IF(B11=0,0,D11/B11) -> 0 | G11: Dividas | H11: =SUMIFS(Lancamentos!$H:$H,Lancamentos!$B:$B,"Despesa",Lancamentos!$C:$C,G11) -> 0 | I11: =IF(SUM(H2:H14)=0,0,H11/SUM(H2:H14)) -> 0
A12: 2026-11 | B12: =SUMIFS(Lancamentos!$H:$H,Lancamentos!$B:$B,"Receita",Lancamentos!$I:$I,A12) -> 0 | C12: =SUMIFS(Lancamentos!$H:$H,Lancamentos!$B:$B,"Despesa",Lancamentos!$I:$I,A12) -> 0 | D12: =B12-C12 -> 0 | E12: =IF(B12=0,0,D12/B12) -> 0 | G12: Pets | H12: =SUMIFS(Lancamentos!$H:$H,Lancamentos!$B:$B,"Despesa",Lancamentos!$C:$C,G12) -> 0 | I12: =IF(SUM(H2:H14)=0,0,H12/SUM(H2:H14)) -> 0
A13: 2026-12 | B13: =SUMIFS(Lancamentos!$H:$H,Lancamentos!$B:$B,"Receita",Lancamentos!$I:$I,A13) -> 0 | C13: =SUMIFS(Lancamentos!$H:$H,Lancamentos!$B:$B,"Despesa",Lancamentos!$I:$I,A13) -> 0 | D13: =B13-C13 -> 0 | E13: =IF(B13=0,0,D13/B13) -> 0 | G13: Familia | H13: =SUMIFS(Lancamentos!$H:$H,Lancamentos!$B:$B,"Despesa",Lancamentos!$C:$C,G13) -> 0 | I13: =IF(SUM(H2:H14)=0,0,H13/SUM(H2:H14)) -> 0
A14: Total | B14: =SUM(B2:B13) -> 0 | C14: =SUM(C2:C13) -> 0 | D14: =SUM(D2:D13) -> 0 | E14: =IF(B14=0,0,D14/B14) -> 0 | G14: Outros | H14: =SUMIFS(Lancamentos!$H:$H,Lancamentos!$B:$B,"Despesa",Lancamentos!$C:$C,G14) -> 0 | I14: =IF(SUM(H2:H14)=0,0,H14/SUM(H2:H14)) -> 0

Sheet Dashboard
A1: Dashboard Financeiro Pessoal
A3: Receitas no ano | B3: =SUM('Resumo Mensal'!B2:B13) -> 0
A4: Despesas no ano | B4: =SUM('Resumo Mensal'!C2:C13) -> 0
A5: Saldo no ano | B5: =B3-B4 -> 0
A6: Gasto medio mensal | B6: =AVERAGE('Resumo Mensal'!C2:C13) -> 0
A7: Maior categoria de despesa | B7: =INDEX('Resumo Mensal'!G2:G14,MATCH(MAX('Resumo Mensal'!H2:H14),'Resumo Mensal'!H2:H14,0)) -> Moradia
A10: Resumo visual: use a aba Resumo Mensal para inserir graficos dinamicos/pizza se quiser personalizar no Excel.

Sheet Metas
A1: Categoria | B1: Limite Mensal | C1: Gasto Mes Atual | D1: Diferenca | E1: Status
A2: Moradia | B2: 0 | C2: =SUMIFS(Lancamentos!$H:$H,Lancamentos!$B:$B,"Despesa",Lancamentos!$C:$C,A2,Lancamentos!$I:$I,TEXT(TODAY(),"yyyy-mm")) -> 1200 | D2: =B2-C2 -> -1200 | E2: =IF(B2=0,"Definir meta",IF(D2>=0,"Dentro da meta","Acima da meta")) -> Definir meta
A3: Alimentacao | B3: 0 | C3: =SUMIFS(Lancamentos!$H:$H,Lancamentos!$B:$B,"Despesa",Lancamentos!$C:$C,A3,Lancamentos!$I:$I,TEXT(TODAY(),"yyyy-mm")) -> 650 | D3: =B3-C3 -> -650 | E3: =IF(B3=0,"Definir meta",IF(D3>=0,"Dentro da meta","Acima da meta")) -> Definir meta
A4: Transporte | B4: 0 | C4: =SUMIFS(Lancamentos!$H:$H,Lancamentos!$B:$B,"Despesa",Lancamentos!$C:$C,A4,Lancamentos!$I:$I,TEXT(TODAY(),"yyyy-mm")) -> 220 | D4: =B4-C4 -> -220 | E4: =IF(B4=0,"Definir meta",IF(D4>=0,"Dentro da meta","Acima da meta")) -> Definir meta
A5: Saude | B5: 0 | C5: =SUMIFS(Lancamentos!$H:$H,Lancamentos!$B:$B,"Despesa",Lancamentos!$C:$C,A5,Lancamentos!$I:$I,TEXT(TODAY(),"yyyy-mm")) -> 0 | D5: =B5-C5 -> 0 | E5: =IF(B5=0,"Definir meta",IF(D5>=0,"Dentro da meta","Acima da meta")) -> Definir meta
A6: Educacao | B6: 0 | C6: =SUMIFS(Lancamentos!$H:$H,Lancamentos!$B:$B,"Despesa",Lancamentos!$C:$C,A6,Lancamentos!$I:$I,TEXT(TODAY(),"yyyy-mm")) -> 0 | D6: =B6-C6 -> 0 | E6: =IF(B6=0,"Definir meta",IF(D6>=0,"Dentro da meta","Acima da meta")) -> Definir meta
A7: Lazer | B7: 0 | C7: =SUMIFS(Lancamentos!$H:$H,Lancamentos!$B:$B,"Despesa",Lancamentos!$C:$C,A7,Lancamentos!$I:$I,TEXT(TODAY(),"yyyy-mm")) -> 0 | D7: =B7-C7 -> 0 | E7: =IF(B7=0,"Definir meta",IF(D7>=0,"Dentro da meta","Acima da meta")) -> Definir meta
A8: Assinaturas | B8: 0 | C8: =SUMIFS(Lancamentos!$H:$H,Lancamentos!$B:$B,"Despesa",Lancamentos!$C:$C,A8,Lancamentos!$I:$I,TEXT(TODAY(),"yyyy-mm")) -> 0 | D8: =B8-C8 -> 0 | E8: =IF(B8=0,"Definir meta",IF(D8>=0,"Dentro da meta","Acima da meta")) -> Definir meta
A9: Compras | B9: 0 | C9: =SUMIFS(Lancamentos!$H:$H,Lancamentos!$B:$B,"Despesa",Lancamentos!$C:$C,A9,Lancamentos!$I:$I,TEXT(TODAY(),"yyyy-mm")) -> 0 | D9: =B9-C9 -> 0 | E9: =IF(B9=0,"Definir meta",IF(D9>=0,"Dentro da meta","Acima da meta")) -> Definir meta
A10: Impostos | B10: 0 | C10: =SUMIFS(Lancamentos!$H:$H,Lancamentos!$B:$B,"Despesa",Lancamentos!$C:$C,A10,Lancamentos!$I:$I,TEXT(TODAY(),"yyyy-mm")) -> 0 | D10: =B10-C10 -> 0 | E10: =IF(B10=0,"Definir meta",IF(D10>=0,"Dentro da meta","Acima da meta")) -> Definir meta
A11: Dividas | B11: 0 | C11: =SUMIFS(Lancamentos!$H:$H,Lancamentos!$B:$B,"Despesa",Lancamentos!$C:$C,A11,Lancamentos!$I:$I,TEXT(TODAY(),"yyyy-mm")) -> 0 | D11: =B11-C11 -> 0 | E11: =IF(B11=0,"Definir meta",IF(D11>=0,"Dentro da meta","Acima da meta")) -> Definir meta
A12: Pets | B12: 0 | C12: =SUMIFS(Lancamentos!$H:$H,Lancamentos!$B:$B,"Despesa",Lancamentos!$C:$C,A12,Lancamentos!$I:$I,TEXT(TODAY(),"yyyy-mm")) -> 0 | D12: =B12-C12 -> 0 | E12: =IF(B12=0,"Definir meta",IF(D12>=0,"Dentro da meta","Acima da meta")) -> Definir meta
A13: Familia | B13: 0 | C13: =SUMIFS(Lancamentos!$H:$H,Lancamentos!$B:$B,"Despesa",Lancamentos!$C:$C,A13,Lancamentos!$I:$I,TEXT(TODAY(),"yyyy-mm")) -> 0 | D13: =B13-C13 -> 0 | E13: =IF(B13=0,"Definir meta",IF(D13>=0,"Dentro da meta","Acima da meta")) -> Definir meta
A14: Outros | B14: 0 | C14: =SUMIFS(Lancamentos!$H:$H,Lancamentos!$B:$B,"Despesa",Lancamentos!$C:$C,A14,Lancamentos!$I:$I,TEXT(TODAY(),"yyyy-mm")) -> 0 | D14: =B14-C14 -> 0 | E14: =IF(B14=0,"Definir meta",IF(D14>=0,"Dentro da meta","Acima da meta")) -> Definir meta

Sheet Ajuda
A1: Como usar
A2: 1. Preencha a aba Lancamentos com receitas e despesas.
A3: 2. Use valores positivos; o campo Tipo define se e receita ou despesa.
A4: 3. Edite listas na aba Categorias para adaptar sua vida real.
A5: 4. Defina limites na aba Metas para controlar o mes atual.
A6: 5. O Resumo Mensal e o Dashboard recalculam ao abrir a planilha.
A7: 6. Para outro ano, altere os meses do Resumo Mensal no formato AAAA-MM.
